boolcalc/__init__.py
boolcalc-0.0.1.dist-info/LICENCE.txt
boolcalc-0.0.1.dist-info/METADATA
boolcalc-0.0.1.dist-info/WHEEL
boolcalc-0.0.1.dist-info/top_level.txt
boolcalc-0.0.1.dist-info/RECORD
