Metadata-Version: 2.1
Name: boolcalc
Version: 0.0.1
Summary: basic boolean calculator
Home-page: UNKNOWN
Author: Otsuka Yuno
Author-email: moreseus@outlook.com
License: MIT
Keywords: calculator
Platform: UNKNOWN
Classifier: Development Status :: 5 - Production/Stable
Classifier: Intended Audience :: Education
Classifier: Operating System :: Microsoft :: Windows :: Windows 10
Classifier: License :: OSI Approved :: MIT License
Classifier: Programming Language :: Python :: 3
